[
  {
    "event": "UFC 128: Shogun vs Jones",
    "fighter1": "Jon Jones",
    "fighter2": "Mauricio Rua"
  },
  {
    "event": "UFC 128: Shogun vs Jones",
    "fighter1": "Urijah Faber",
    "fighter2": "Eddie Wineland"
  },
  {
    "event": "UFC 128: Shogun vs Jones",
    "fighter1": "Jim Miller",
    "fighter2": "Kamal Shalorus"
  },
  {
    "event": "UFC 128: Shogun vs Jones",
    "fighter1": "Nate Marquardt",
    "fighter2": "Dan Miller"
  },
  {
    "event": "UFC 128: Shogun vs Jones",
    "fighter1": "Brendan Schaub",
    "fighter2": "Mirko Filipovic"
  },
  {
    "event": "UFC 128: Shogun vs Jones",
    "fighter1": "Luiz Cane",
    "fighter2": "Eliot Marshall"
  },
  {
    "event": "UFC 128: Shogun vs Jones",
    "fighter1": "Edson Barboza",
    "fighter2": "Anthony Njokuani"
  },
  {
    "event": "UFC 128: Shogun vs Jones",
    "fighter1": "Mike Pyle",
    "fighter2": "Ricardo Almeida"
  },
  {
    "event": "UFC 128: Shogun vs Jones",
    "fighter1": "Gleison Tibau",
    "fighter2": "Kurt Pellegrino"
  },
  {
    "event": "UFC 128: Shogun vs Jones",
    "fighter1": "Joseph Benavidez",
    "fighter2": "Ian Loveland"
  },
  {
    "event": "UFC 128: Shogun vs Jones",
    "fighter1": "Nick Catone",
    "fighter2": "Constantinos Philippou"
  },
  {
    "event": "UFC 128: Shogun vs Jones",
    "fighter1": "Erik Koch",
    "fighter2": "Raphael Assuncao"
  }
]