[
  {
    "event": "UFC 109: Relentless",
    "fighter1": "Randy Couture",
    "fighter2": "Mark Coleman"
  },
  {
    "event": "UFC 109: Relentless",
    "fighter1": "Chael Sonnen",
    "fighter2": "Nate Marquardt"
  },
  {
    "event": "UFC 109: Relentless",
    "fighter1": "Paulo Thiago",
    "fighter2": "Mike Swick"
  },
  {
    "event": "UFC 109: Relentless",
    "fighter1": "Demian Maia",
    "fighter2": "Dan Miller"
  },
  {
    "event": "UFC 109: Relentless",
    "fighter1": "Matt Serra",
    "fighter2": "Frank Trigg"
  },
  {
    "event": "UFC 109: Relentless",
    "fighter1": "Mac Danzig",
    "fighter2": "Justin Buchholz"
  },
  {
    "event": "UFC 109: Relentless",
    "fighter1": "Melvin Guillard",
    "fighter2": "Ronys Torres"
  },
  {
    "event": "UFC 109: Relentless",
    "fighter1": "Rob Emerson",
    "fighter2": "Phillipe Nover"
  },
  {
    "event": "UFC 109: Relentless",
    "fighter1": "Phil Davis",
    "fighter2": "Brian Stann"
  },
  {
    "event": "UFC 109: Relentless",
    "fighter1": "Chris Tuchscherer",
    "fighter2": "Tim Hague"
  },
  {
    "event": "UFC 109: Relentless",
    "fighter1": "Joey Beltran",
    "fighter2": "Rolles Gracie"
  }
]