[
  {
    "event": "UFC 171: Hendricks vs Lawler",
    "fighter1": "Johny Hendricks",
    "fighter2": "Robbie Lawler"
  },
  {
    "event": "UFC 171: Hendricks vs Lawler",
    "fighter1": "Tyron Woodley",
    "fighter2": "Carlos Condit"
  },
  {
    "event": "UFC 171: Hendricks vs Lawler",
    "fighter1": "Myles Jury",
    "fighter2": "Diego Sanchez"
  },
  {
    "event": "UFC 171: Hendricks vs Lawler",
    "fighter1": "Hector Lombard",
    "fighter2": "Jake Shields"
  },
  {
    "event": "UFC 171: Hendricks vs Lawler",
    "fighter1": "Ovince Saint Preux",
    "fighter2": "Nikita Krylov"
  },
  {
    "event": "UFC 171: Hendricks vs Lawler",
    "fighter1": "Kelvin Gastelum",
    "fighter2": "Rick Story"
  },
  {
    "event": "UFC 171: Hendricks vs Lawler",
    "fighter1": "Jessica Andrade",
    "fighter2": "Raquel Pennington"
  },
  {
    "event": "UFC 171: Hendricks vs Lawler",
    "fighter1": "Dennis Bermudez",
    "fighter2": "Jimy Hettes"
  },
  {
    "event": "UFC 171: Hendricks vs Lawler",
    "fighter1": "Alex Garcia",
    "fighter2": "Sean Spencer"
  },
  {
    "event": "UFC 171: Hendricks vs Lawler",
    "fighter1": "Francisco Trevino",
    "fighter2": "Renee Forte"
  },
  {
    "event": "UFC 171: Hendricks vs Lawler",
    "fighter1": "Justin Scoggins",
    "fighter2": "Will Campuzano"
  },
  {
    "event": "UFC 171: Hendricks vs Lawler",
    "fighter1": "Sean Strickland",
    "fighter2": "Robert McDaniel"
  },
  {
    "event": "UFC 171: Hendricks vs Lawler",
    "fighter1": "Robert Whiteford",
    "fighter2": "Daniel Pineda"
  }
]