[
  {
    "event": "UFC 70: Nations Collide",
    "fighter1": "Gabriel Gonzaga",
    "fighter2": "Mirko Filipovic"
  },
  {
    "event": "UFC 70: Nations Collide",
    "fighter1": "Andrei Arlovski",
    "fighter2": "Fabricio Werdum"
  },
  {
    "event": "UFC 70: Nations Collide",
    "fighter1": "Michael Bisping",
    "fighter2": "Elvis Sinosic"
  },
  {
    "event": "UFC 70: Nations Collide",
    "fighter1": "Lyoto Machida",
    "fighter2": "David Heath"
  },
  {
    "event": "UFC 70: Nations Collide",
    "fighter1": "Cheick Kongo",
    "fighter2": "Assuerio Silva"
  },
  {
    "event": "UFC 70: Nations Collide",
    "fighter1": "Terry Etim",
    "fighter2": "Matt Grice"
  },
  {
    "event": "UFC 70: Nations Collide",
    "fighter1": "Junior Assuncao",
    "fighter2": "David Lee"
  },
  {
    "event": "UFC 70: Nations Collide",
    "fighter1": "Alessio Sakara",
    "fighter2": "Victor Valimaki"
  },
  {
    "event": "UFC 70: Nations Collide",
    "fighter1": "Jess Liaudin",
    "fighter2": "Dennis Siver"
  },
  {
    "event": "UFC 70: Nations Collide",
    "fighter1": "Paul Taylor",
    "fighter2": "Edilberto de Oliveira"
  }
]