[
  {
    "event": "UFC 278: Usman vs. Edwards",
    "fighter1": "Leon Edwards",
    "fighter2": "Kamaru Usman"
  },
  {
    "event": "UFC 278: Usman vs. Edwards",
    "fighter1": "Paulo Costa",
    "fighter2": "Luke Rockhold"
  },
  {
    "event": "UFC 278: Usman vs. Edwards",
    "fighter1": "Merab Dvalishvili",
    "fighter2": "Jose Aldo"
  },
  {
    "event": "UFC 278: Usman vs. Edwards",
    "fighter1": "Lucie Pudilova",
    "fighter2": "Wu Yanan"
  },
  {
    "event": "UFC 278: Usman vs. Edwards",
    "fighter1": "Tyson Pedro",
    "fighter2": "Harry Hunsucker"
  },
  {
    "event": "UFC 278: Usman vs. Edwards",
    "fighter1": "Marcin Tybura",
    "fighter2": "Alexandr Romanov"
  },
  {
    "event": "UFC 278: Usman vs. Edwards",
    "fighter1": "Jared Gordon",
    "fighter2": "Leonardo Santos"
  },
  {
    "event": "UFC 278: Usman vs. Edwards",
    "fighter1": "Sean Woodson",
    "fighter2": "Luis Saldana"
  },
  {
    "event": "UFC 278: Usman vs. Edwards",
    "fighter1": "Ange Loosa",
    "fighter2": "AJ Fletcher"
  },
  {
    "event": "UFC 278: Usman vs. Edwards",
    "fighter1": "Amir Albazi",
    "fighter2": "Francisco Figueiredo"
  },
  {
    "event": "UFC 278: Usman vs. Edwards",
    "fighter1": "Aoriqileng",
    "fighter2": "Jay Perrin"
  },
  {
    "event": "UFC 278: Usman vs. Edwards",
    "fighter1": "Victor Altamirano",
    "fighter2": "Daniel Lacerda"
  }
]