[
  {
    "event": "UFC Fight Night: Blachowicz vs. Santos",
    "fighter1": "Thiago Santos",
    "fighter2": "Jan Blachowicz"
  },
  {
    "event": "UFC Fight Night: Blachowicz vs. Santos",
    "fighter1": "Stefan Struve",
    "fighter2": "Marcos Rogerio de Lima"
  },
  {
    "event": "UFC Fight Night: Blachowicz vs. Santos",
    "fighter1": "Michal Oleksiejczuk",
    "fighter2": "Gian Villante"
  },
  {
    "event": "UFC Fight Night: Blachowicz vs. Santos",
    "fighter1": "Liz Carmouche",
    "fighter2": "Lucie Pudilova"
  },
  {
    "event": "UFC Fight Night: Blachowicz vs. Santos",
    "fighter1": "Petr Yan",
    "fighter2": "John Dodson"
  },
  {
    "event": "UFC Fight Night: Blachowicz vs. Santos",
    "fighter1": "Magomed Ankalaev",
    "fighter2": "Klidson Abreu"
  },
  {
    "event": "UFC Fight Night: Blachowicz vs. Santos",
    "fighter1": "Dwight Grant",
    "fighter2": "Carlo Pedersoli Jr."
  },
  {
    "event": "UFC Fight Night: Blachowicz vs. Santos",
    "fighter1": "Chris Fishgold",
    "fighter2": "Daniel Teymur"
  },
  {
    "event": "UFC Fight Night: Blachowicz vs. Santos",
    "fighter1": "Gillian Robertson",
    "fighter2": "Veronica Hardy"
  },
  {
    "event": "UFC Fight Night: Blachowicz vs. Santos",
    "fighter1": "Damir Hadzovic",
    "fighter2": "Marco Polo Reyes"
  },
  {
    "event": "UFC Fight Night: Blachowicz vs. Santos",
    "fighter1": "Ismail Naurdiev",
    "fighter2": "Michel Prazeres"
  },
  {
    "event": "UFC Fight Night: Blachowicz vs. Santos",
    "fighter1": "Diego Ferreira",
    "fighter2": "Rustam Khabilov"
  },
  {
    "event": "UFC Fight Night: Blachowicz vs. Santos",
    "fighter1": "Damir Ismagulov",
    "fighter2": "Joel Alvarez"
  }
]