[
  {
    "event": "UFC 201: Lawler vs. Woodley",
    "fighter1": "Tyron Woodley",
    "fighter2": "Robbie Lawler"
  },
  {
    "event": "UFC 201: Lawler vs. Woodley",
    "fighter1": "Karolina Kowalkiewicz",
    "fighter2": "Rose Namajunas"
  },
  {
    "event": "UFC 201: Lawler vs. Woodley",
    "fighter1": "Jake Ellenberger",
    "fighter2": "Matt Brown"
  },
  {
    "event": "UFC 201: Lawler vs. Woodley",
    "fighter1": "Erik Perez",
    "fighter2": "Francisco Rivera"
  },
  {
    "event": "UFC 201: Lawler vs. Woodley",
    "fighter1": "Ryan Benoit",
    "fighter2": "Fredy Serrano"
  },
  {
    "event": "UFC 201: Lawler vs. Woodley",
    "fighter1": "Nikita Krylov",
    "fighter2": "Ed Herman"
  },
  {
    "event": "UFC 201: Lawler vs. Woodley",
    "fighter1": "Jorge Masvidal",
    "fighter2": "Ross Pearson"
  },
  {
    "event": "UFC 201: Lawler vs. Woodley",
    "fighter1": "Anthony Hamilton",
    "fighter2": "Damian Grabowski"
  },
  {
    "event": "UFC 201: Lawler vs. Woodley",
    "fighter1": "Wilson Reis",
    "fighter2": "Hector Sandoval"
  },
  {
    "event": "UFC 201: Lawler vs. Woodley",
    "fighter1": "Michael Graves",
    "fighter2": "Bojan Velickovic"
  },
  {
    "event": "UFC 201: Lawler vs. Woodley",
    "fighter1": "Damien Brown",
    "fighter2": "Cesar Arzamendia"
  }
]