[
  {
    "event": "UFC 41: Onslaught",
    "fighter1": "Tim Sylvia",
    "fighter2": "Ricco Rodriguez"
  },
  {
    "event": "UFC 41: Onslaught",
    "fighter1": "Frank Mir",
    "fighter2": "David Abbott"
  },
  {
    "event": "UFC 41: Onslaught",
    "fighter1": "BJ Penn",
    "fighter2": "Caol Uno"
  },
  {
    "event": "UFC 41: Onslaught",
    "fighter1": "Matt Lindland",
    "fighter2": "Phil Baroni"
  },
  {
    "event": "UFC 41: Onslaught",
    "fighter1": "Vladimir Matyushenko",
    "fighter2": "Pedro Rizzo"
  },
  {
    "event": "UFC 41: Onslaught",
    "fighter1": "Din Thomas",
    "fighter2": "Matt Serra"
  },
  {
    "event": "UFC 41: Onslaught",
    "fighter1": "Gan McGee",
    "fighter2": "Alexandre Dantas"
  },
  {
    "event": "UFC 41: Onslaught",
    "fighter1": "Yves Edwards",
    "fighter2": "Rich Clementi"
  }
]