[
  {
    "event": "UFC Fight Night: Dern vs. Rodriguez",
    "fighter1": "Marina Rodriguez",
    "fighter2": "Mackenzie Dern"
  },
  {
    "event": "UFC Fight Night: Dern vs. Rodriguez",
    "fighter1": "Randy Brown",
    "fighter2": "Jared Gooden"
  },
  {
    "event": "UFC Fight Night: Dern vs. Rodriguez",
    "fighter1": "Matheus Nicolau",
    "fighter2": "Tim Elliott"
  },
  {
    "event": "UFC Fight Night: Dern vs. Rodriguez",
    "fighter1": "Mariya Agapova",
    "fighter2": "Sabina Mazo"
  },
  {
    "event": "UFC Fight Night: Dern vs. Rodriguez",
    "fighter1": "Chris Gutierrez",
    "fighter2": "Felipe Colares"
  },
  {
    "event": "UFC Fight Night: Dern vs. Rodriguez",
    "fighter1": "Alexandr Romanov",
    "fighter2": "Jared Vanderaa"
  },
  {
    "event": "UFC Fight Night: Dern vs. Rodriguez",
    "fighter1": "Damon Jackson",
    "fighter2": "Charles Rosa"
  },
  {
    "event": "UFC Fight Night: Dern vs. Rodriguez",
    "fighter1": "Loopy Godinez",
    "fighter2": "Silvana Gomez Juarez"
  },
  {
    "event": "UFC Fight Night: Dern vs. Rodriguez",
    "fighter1": "Steve Garcia",
    "fighter2": "Charlie Ontiveros"
  }
]