[
  {
    "event": "UFC 28: High Stakes",
    "fighter1": "Randy Couture",
    "fighter2": "Kevin Randleman"
  },
  {
    "event": "UFC 28: High Stakes",
    "fighter1": "Renato Sobral",
    "fighter2": "Maurice Smith"
  },
  {
    "event": "UFC 28: High Stakes",
    "fighter1": "Josh Barnett",
    "fighter2": "Gan McGee"
  },
  {
    "event": "UFC 28: High Stakes",
    "fighter1": "Andrei Arlovski",
    "fighter2": "Aaron Brink"
  },
  {
    "event": "UFC 28: High Stakes",
    "fighter1": "Jens Pulver",
    "fighter2": "John Lewis"
  },
  {
    "event": "UFC 28: High Stakes",
    "fighter1": "Mark Hughes",
    "fighter2": "Alex Stiebling"
  },
  {
    "event": "UFC 28: High Stakes",
    "fighter1": "Ben Earwood",
    "fighter2": "Chris Lytle"
  }
]