[
  {
    "event": "UFC Fight Night: Lawler vs. Dos Anjos",
    "fighter1": "Rafael Dos Anjos",
    "fighter2": "Robbie Lawler"
  },
  {
    "event": "UFC Fight Night: Lawler vs. Dos Anjos",
    "fighter1": "Josh Emmett",
    "fighter2": "Ricardo Lamas"
  },
  {
    "event": "UFC Fight Night: Lawler vs. Dos Anjos",
    "fighter1": "Santiago Ponzinibbio",
    "fighter2": "Mike Perry"
  },
  {
    "event": "UFC Fight Night: Lawler vs. Dos Anjos",
    "fighter1": "Glover Teixeira",
    "fighter2": "Misha Cirkunov"
  },
  {
    "event": "UFC Fight Night: Lawler vs. Dos Anjos",
    "fighter1": "Jan Blachowicz",
    "fighter2": "Jared Cannonier"
  },
  {
    "event": "UFC Fight Night: Lawler vs. Dos Anjos",
    "fighter1": "Julian Marquez",
    "fighter2": "Darren Stewart"
  },
  {
    "event": "UFC Fight Night: Lawler vs. Dos Anjos",
    "fighter1": "Chad Laprise",
    "fighter2": "Galore Bofando"
  },
  {
    "event": "UFC Fight Night: Lawler vs. Dos Anjos",
    "fighter1": "Nordine Taleb",
    "fighter2": "Danny Roberts"
  },
  {
    "event": "UFC Fight Night: Lawler vs. Dos Anjos",
    "fighter1": "John Makdessi",
    "fighter2": "Abel Trujillo"
  },
  {
    "event": "UFC Fight Night: Lawler vs. Dos Anjos",
    "fighter1": "Alessio Di Chirico",
    "fighter2": "Oluwale Bamgbose"
  },
  {
    "event": "UFC Fight Night: Lawler vs. Dos Anjos",
    "fighter1": "Jordan Mein",
    "fighter2": "Erick Silva"
  }
]